m2r3/__init__.py
m2r3/cli/__init__.py
m2r3/cli/m2r2.py
m2r3/constants.py
m2r3/directives.py
m2r3/m2r2.py
m2r3/parser.py
m2r3/rst_parser.py
m2r3/rst_renderer.py
m2r3/sphinx_m2r2.py
m2r3/typing.py
m2r3-2.0.0rc1.dist-info/LICENSE
m2r3-2.0.0rc1.dist-info/METADATA
m2r3-2.0.0rc1.dist-info/WHEEL
m2r3-2.0.0rc1.dist-info/entry_points.txt
m2r3-2.0.0rc1.dist-info/RECORD
